karrio/__init__.py
karrio/api_client.py
karrio/configuration.py
karrio/exceptions.py
karrio/model_utils.py
karrio/rest.py
karrio/api/__init__.py
karrio/api/addresses_api.py
karrio/api/api_api.py
karrio/api/carriers_api.py
karrio/api/customs_api.py
karrio/api/orders_api.py
karrio/api/parcels_api.py
karrio/api/pickups_api.py
karrio/api/proxy_api.py
karrio/api/shipments_api.py
karrio/api/trackers_api.py
karrio/api/webhooks_api.py
karrio/apis/__init__.py
karrio/model/__init__.py
karrio/model/address.py
karrio/model/address_data.py
karrio/model/address_list.py
karrio/model/address_validation.py
karrio/model/carrier_list.py
karrio/model/carrier_settings.py
karrio/model/charge.py
karrio/model/commodity.py
karrio/model/commodity_data.py
karrio/model/customs.py
karrio/model/customs_data.py
karrio/model/customs_list.py
karrio/model/documents.py
karrio/model/duty.py
karrio/model/error_response.py
karrio/model/message.py
karrio/model/metadata.py
karrio/model/operation.py
karrio/model/operation_confirmation.py
karrio/model/operation_response.py
karrio/model/order.py
karrio/model/order_data.py
karrio/model/order_list.py
karrio/model/order_update_data.py
karrio/model/parcel.py
karrio/model/parcel_data.py
karrio/model/parcel_list.py
karrio/model/payment.py
karrio/model/pickup.py
karrio/model/pickup_cancel_data.py
karrio/model/pickup_cancel_request.py
karrio/model/pickup_data.py
karrio/model/pickup_list.py
karrio/model/pickup_request.py
karrio/model/pickup_response.py
karrio/model/pickup_update_data.py
karrio/model/pickup_update_request.py
karrio/model/rate.py
karrio/model/rate_request.py
karrio/model/rate_response.py
karrio/model/references.py
karrio/model/shipment.py
karrio/model/shipment_cancel_request.py
karrio/model/shipment_data.py
karrio/model/shipment_list.py
karrio/model/shipment_purchase_data.py
karrio/model/shipment_rate_data.py
karrio/model/shipment_update_data.py
karrio/model/shipping_request.py
karrio_python-2022.3.dist-info/METADATA
karrio_python-2022.3.dist-info/RECORD
karrio_python-2022.3.dist-info/WHEEL
karrio_python-2022.3.dist-info/top_level.txt
