Metadata-Version: 2.1
Name: karrio-python
Version: 2022.3
Summary: karrio universal Shipping API Python client library
Home-page: https://github.com/karrioapi/karrio-python
Author-email: hello@karrio.io
License: UNKNOWN
Keywords: Karrio,Multi-carrier API,Shipping API
Platform: UNKNOWN
Classifier: Programming Language :: Python :: 3
Classifier: License :: OSI Approved :: MIT License
Classifier: Operating System :: OS Independent
Requires-Python: >=3.6
Requires-Dist: urllib3 (>=1.25.3)
Requires-Dist: python-dateutil
